illallangi/django/swimming/__init__.py
illallangi/django/swimming/__version__.py
illallangi/django/swimming/apps.py
illallangi/django/swimming/adapters/__init__.py
illallangi/django/swimming/adapters/swimming.py
illallangi/django/swimming/admin/__init__.py
illallangi/django/swimming/admin/swim.py
illallangi/django/swimming/diffsyncmodels/__init__.py
illallangi/django/swimming/diffsyncmodels/swim.py
illallangi/django/swimming/management/__init__.py
illallangi/django/swimming/management/commands/__init__.py
illallangi/django/swimming/management/commands/syncswimming.py
illallangi/django/swimming/migrations/0001_initial.py
illallangi/django/swimming/migrations/__init__.py
illallangi/django/swimming/models/__init__.py
illallangi/django/swimming/models/swim.py
illallangi/django/swimming/static/swimming/swims.png
illallangi/django/swimming/templates/swimming/home.html
illallangi/django/swimming/templates/swimming/swim.html
illallangi/django/swimming/templates/swimming/swims.html
illallangi/django/swimming/urls/__init__.py
illallangi/django/swimming/urls/swim.py
illallangi/django/swimming/views/__init__.py
illallangi/django/swimming/views/favicon.py
illallangi/django/swimming/views/home/__init__.py
illallangi/django/swimming/views/home/home_html.py
illallangi/django/swimming/views/swim/__init__.py
illallangi/django/swimming/views/swim/swim_html.py
illallangi/django/swimming/views/swim/swims_html.py
illallangi_django_swimming-0.1.1.dist-info/METADATA
illallangi_django_swimming-0.1.1.dist-info/WHEEL
illallangi_django_swimming-0.1.1.dist-info/licenses/LICENSE
illallangi_django_swimming-0.1.1.dist-info/RECORD
